README.md
existence.py
setup.py
existence.egg-info/PKG-INFO
existence.egg-info/SOURCES.txt
existence.egg-info/dependency_links.txt
existence.egg-info/entry_points.txt
existence.egg-info/requires.txt
existence.egg-info/top_level.txt