Metadata-Version: 2.1
Name: existence
Version: 0.3.0
Summary: Checks static .html files for bad links
Home-page: https://github.com/ckcollab/existence
Author: Eric Carmichael
Author-email: eric@ckcollab.com
License: MIT
Keywords: link checker
Platform: UNKNOWN
Classifier: Intended Audience :: Developers
Classifier: Natural Language :: English
Classifier: License :: OSI Approved :: MIT License
Classifier: Operating System :: OS Independent
Classifier: Programming Language :: Python
Classifier: Programming Language :: Python :: 3
Classifier: Topic :: Software Development :: Libraries :: Python Modules
